safentic/__init__.py
safentic/config.py
safentic/decorators.py
safentic/layer.py
safentic/policy_enforcer.py
safentic/policy_engine.py
safentic/_internal/errors.py
safentic/adapters/mcp_adapter.py
safentic/cli/__init__.py
safentic/cli/main.py
safentic/cli/utils.py
safentic/cli/commands/check_tool.py
safentic/cli/commands/logs.py
safentic/cli/commands/validate_policy.py
safentic/helper/__init__.py
safentic/helper/helper.py
safentic/logger/__init__.py
safentic/logger/audit.py
safentic/verifiers/__init__.py
safentic/verifiers/llm_verifier.py
safentic-1.0.8.dist-info/licenses/LICENSE.txt
safentic_poc/backend/__init__.py
safentic_poc/backend/api/__init__.py
safentic_poc/backend/api/main.py
safentic-1.0.8.dist-info/METADATA
safentic-1.0.8.dist-info/WHEEL
safentic-1.0.8.dist-info/entry_points.txt
safentic-1.0.8.dist-info/top_level.txt
safentic-1.0.8.dist-info/RECORD
