Metadata-Version: 2.4
Name: safentic
Version: 1.0.8
Summary: Safentic SDK for AI agent runtime enforcement interception.
Author-email: Safentic <contact@safentic.com>
License-Expression: LicenseRef-Proprietary
Project-URL: Homepage, https://safentic.com
Classifier: Programming Language :: Python :: 3
Classifier: Operating System :: OS Independent
Requires-Python: >=3.10
License-File: LICENSE.txt
Requires-Dist: PyYAML
Requires-Dist: langchain
Requires-Dist: langchain-community
Requires-Dist: langchain-openai
Requires-Dist: openai
Requires-Dist: python-dotenv
Requires-Dist: sentence-transformers==3.2.1
Requires-Dist: requests
Requires-Dist: SQLAlchemy
Provides-Extra: dev
Requires-Dist: pytest; extra == "dev"
Requires-Dist: coverage; extra == "dev"
Requires-Dist: black; extra == "dev"
Requires-Dist: isort; extra == "dev"
Requires-Dist: ruff; extra == "dev"
Requires-Dist: mypy; extra == "dev"
Requires-Dist: pip-audit-extra; extra == "dev"
Requires-Dist: types-requests; extra == "dev"
Requires-Dist: types-PyYAML; extra == "dev"
Dynamic: license-file
